fastest_pkg/__init__.py
fastest_pkg/fastest_pkg.py
fastest_pkg/utils/__init__.py
fastest_pkg/utils/human_bytes.py
fastest_pkg/utils/pkg_mirror.py
fastest_pkg-0.2.3.dist-info/METADATA
fastest_pkg-0.2.3.dist-info/WHEEL
fastest_pkg-0.2.3.dist-info/entry_points.txt
fastest_pkg-0.2.3.dist-info/top_level.txt
fastest_pkg-0.2.3.dist-info/zip-safe
fastest_pkg-0.2.3.dist-info/RECORD
