Metadata-Version: 2.4
Name: fastest_pkg
Version: 0.2.3
Summary: Script to find the fastest FreeBSD.org pkg mirror
Home-page: https://github.com/ehaupt/fastest_pkg
Author: Emanuel Haupt
Author-email: ehaupt@FreeBSD.org
License: BSD 3-Clause License
Keywords: FreeBSD,fastest pkg mirror
Classifier: Programming Language :: Python :: 3
Classifier: Topic :: Utilities
Classifier: License :: OSI Approved :: BSD License
Requires-Dist: dnspython
Requires-Dist: pycurl
